mycalc/calculator.py
kimminseo1234-0.1.dist-info/METADATA
kimminseo1234-0.1.dist-info/WHEEL
kimminseo1234-0.1.dist-info/top_level.txt
kimminseo1234-0.1.dist-info/RECORD
