Metadata-Version: 2.1
Name: kimminseo1234
Version: 0.1
Summary: nice calculator
Home-page: https://github.com/Narae00
Download-URL: https://github.com/Narae00
Author: minseo
License: UNKNOWN
Platform: UNKNOWN
Classifier: Programming Language :: Python :: 3
